kubeflow/__init__.py
kubeflow/pytorchjob/__init__.py
kubeflow/pytorchjob/api_client.py
kubeflow/pytorchjob/configuration.py
kubeflow/pytorchjob/rest.py
kubeflow/pytorchjob/api/__init__.py
kubeflow/pytorchjob/api/py_torch_job_client.py
kubeflow/pytorchjob/api/py_torch_job_watch.py
kubeflow/pytorchjob/constants/__init__.py
kubeflow/pytorchjob/constants/constants.py
kubeflow/pytorchjob/models/__init__.py
kubeflow/pytorchjob/models/v1_job_condition.py
kubeflow/pytorchjob/models/v1_job_status.py
kubeflow/pytorchjob/models/v1_py_torch_job.py
kubeflow/pytorchjob/models/v1_py_torch_job_list.py
kubeflow/pytorchjob/models/v1_py_torch_job_spec.py
kubeflow/pytorchjob/models/v1_replica_spec.py
kubeflow/pytorchjob/models/v1_replica_status.py
kubeflow/pytorchjob/models/v1_time.py
kubeflow/pytorchjob/utils/__init__.py
kubeflow/pytorchjob/utils/utils.py
test/__init__.py
test/test_e2e.py
test/test_v1_job_condition.py
test/test_v1_job_status.py
test/test_v1_py_torch_job.py
test/test_v1_py_torch_job_list.py
test/test_v1_py_torch_job_spec.py
test/test_v1_replica_spec.py
test/test_v1_replica_status.py
kubeflow_pytorchjob-0.1.3.dist-info/METADATA
kubeflow_pytorchjob-0.1.3.dist-info/WHEEL
kubeflow_pytorchjob-0.1.3.dist-info/top_level.txt
kubeflow_pytorchjob-0.1.3.dist-info/RECORD
